[{"place_id": 25838029, "licence": "Data \u00a9 OpenStreetMap contributors, ODbL 1.0. https://osm.org/copyright", "osm_type": "node", "osm_id": 2732467292, "boundingbox": ["52.551475", "52.551575", "5.9128732", "5.9129732"], "lat": "52.551525", "lon": "5.9129232", "display_name": "Gemeente Kampen, 1, Burgemeester Berghuisplein, Binnenstad, Kampen, Overijssel, Netherlands, 8261 DD, Netherlands", "class": "place", "type": "house", "importance": 0.21000999999999997, "geojson": {"type": "Point", "coordinates": [5.9129232, 52.551525]}}]